waveshare_epd_driver/__init__.py
waveshare_epd_driver/epd1in02.py
waveshare_epd_driver/epd1in54.py
waveshare_epd_driver/epd1in54_V2.py
waveshare_epd_driver/epd1in54b.py
waveshare_epd_driver/epd1in54b_V2.py
waveshare_epd_driver/epd1in54c.py
waveshare_epd_driver/epd2in13.py
waveshare_epd_driver/epd2in13_V2.py
waveshare_epd_driver/epd2in13_V3.py
waveshare_epd_driver/epd2in13b_V3.py
waveshare_epd_driver/epd2in13bc.py
waveshare_epd_driver/epd2in13d.py
waveshare_epd_driver/epd2in66.py
waveshare_epd_driver/epd2in66b.py
waveshare_epd_driver/epd2in7.py
waveshare_epd_driver/epd2in7b.py
waveshare_epd_driver/epd2in7b_V2.py
waveshare_epd_driver/epd2in9.py
waveshare_epd_driver/epd2in9_V2.py
waveshare_epd_driver/epd2in9b_V3.py
waveshare_epd_driver/epd2in9bc.py
waveshare_epd_driver/epd2in9d.py
waveshare_epd_driver/epd3in7.py
waveshare_epd_driver/epd4in01f.py
waveshare_epd_driver/epd4in2.py
waveshare_epd_driver/epd4in2b_V2.py
waveshare_epd_driver/epd4in2bc.py
waveshare_epd_driver/epd5in65f.py
waveshare_epd_driver/epd5in83.py
waveshare_epd_driver/epd5in83_V2.py
waveshare_epd_driver/epd5in83b_V2.py
waveshare_epd_driver/epd5in83bc.py
waveshare_epd_driver/epd7in5.py
waveshare_epd_driver/epd7in5_HD.py
waveshare_epd_driver/epd7in5_V2.py
waveshare_epd_driver/epd7in5b_HD.py
waveshare_epd_driver/epd7in5b_V2.py
waveshare_epd_driver/epd7in5bc.py
waveshare_epd_driver/epdconfig.py
waveshare_epd_driver-1.0.0.dist-info/METADATA
waveshare_epd_driver-1.0.0.dist-info/WHEEL
waveshare_epd_driver-1.0.0.dist-info/top_level.txt
waveshare_epd_driver-1.0.0.dist-info/RECORD
